helper_hwp/__init__.py
helper_hwp/char_paragraph.py
helper_hwp/cli.py
helper_hwp/constants.py
helper_hwp/document_structure.py
helper_hwp/models.py
helper_hwp/parsed_elements.py
helper_hwp/parser.py
helper_hwp/record_stream.py
helper_hwp/requirements_rnac.py
helper_hwp/utils.py
helper_hwp-0.5.5.dist-info/licenses/LICENSE
helper_hwp-0.5.5.dist-info/METADATA
helper_hwp-0.5.5.dist-info/WHEEL
helper_hwp-0.5.5.dist-info/entry_points.txt
helper_hwp-0.5.5.dist-info/top_level.txt
helper_hwp-0.5.5.dist-info/RECORD
