Metadata-Version: 2.4
Name: helper-hwp
Version: 0.5.5
Summary: Python HWP 파일 파서 및 텍스트 추출 라이브러리
Author-email: c0z0c <c0z0c.dev@gmail.com>
License: Apache-2.0
Project-URL: Homepage, https://github.com/c0z0c-helper/helper_hwp
Project-URL: Repository, https://github.com/c0z0c-helper/helper_hwp
Project-URL: Issues, https://github.com/c0z0c-helper/helper_hwp/issues
Keywords: hwp,hancom,hangul,parser,text-extraction
Classifier: Development Status :: 3 - Alpha
Classifier: Intended Audience :: Developers
Classifier: License :: OSI Approved :: Apache Software License
Classifier: Programming Language :: Python :: 3
Classifier: Programming Language :: Python :: 3.8
Classifier: Programming Language :: Python :: 3.9
Classifier: Programming Language :: Python :: 3.10
Classifier: Programming Language :: Python :: 3.11
Classifier: Programming Language :: Python :: 3.12
Classifier: Topic :: Software Development :: Libraries :: Python Modules
Classifier: Topic :: Text Processing
Requires-Python: >=3.8
License-File: LICENSE
Requires-Dist: olefile>=0.46
Requires-Dist: pycryptodome>=3.15.0
Provides-Extra: dev
Requires-Dist: pytest>=7.0.0; extra == "dev"
Requires-Dist: pytest-cov>=4.0.0; extra == "dev"
Requires-Dist: black>=23.0.0; extra == "dev"
Requires-Dist: ruff>=0.1.0; extra == "dev"
Requires-Dist: mypy>=1.0.0; extra == "dev"
Provides-Extra: doc
Requires-Dist: helper-md-doc>=0.1.0; extra == "doc"
Provides-Extra: pdf
Requires-Dist: helper-md-doc>=0.1.0; extra == "pdf"
Requires-Dist: playwright>=1.40.0; extra == "pdf"
Dynamic: license-file
